printjson/__init__.py
printjson-1.0.1.dist-info/DESCRIPTION.rst
printjson-1.0.1.dist-info/METADATA
printjson-1.0.1.dist-info/RECORD
printjson-1.0.1.dist-info/WHEEL
printjson-1.0.1.dist-info/entry_points.txt
printjson-1.0.1.dist-info/metadata.json
printjson-1.0.1.dist-info/top_level.txt
